{
  "cli": {
    "version": ">= 5.0.0",
    "requireCommit": true
  },
  "build": {
    "development": {
      "developmentClient": true,
      "distribution": "internal"
    },
    "preview": {
      "channel": "preview",
      "distribution": "internal",
      "android": {
        "buildType": "apk"
      },
      "ios": {
        "simulator": false
      },
      "env": {
        "EXPO_PUBLIC_CRM_URL": "https://hearing-hope-crm.vercel.app"
      }
    },
    "production": {
      "channel": "production",
      "android": {
        "buildType": "apk"
      },
      "env": {
        "EXPO_PUBLIC_CRM_URL": "https://hearing-hope-crm.vercel.app"
      }
    }
  },
  "submit": {
    "production": {}
  }
}
